openinverter_can_tool/__init__.py
openinverter_can_tool/__main__.py
openinverter_can_tool/can_upgrade.py
openinverter_can_tool/cli.py
openinverter_can_tool/constants.py
openinverter_can_tool/fpfloat.py
openinverter_can_tool/gui.py
openinverter_can_tool/map_persistence.py
openinverter_can_tool/oi_node.py
openinverter_can_tool/param_utils.py
openinverter_can_tool/paramdb.py
openinverter_can_tool/remote_db.py
openinverter_can_tool/scanner.py
openinverter_can_tool-0.5.0.data/data/docs/CONTRIBUTING.md
openinverter_can_tool-0.5.0.data/data/docs/can-mapping.md
openinverter_can_tool-0.5.0.data/data/docs/gui-readme.md
openinverter_can_tool-0.5.0.data/data/docs/openinverter_can_tool_tkinter_gui_parameters.png
openinverter_can_tool-0.5.0.data/data/docs/savvycan-inverter-temperatures-interpreted.png
openinverter_can_tool-0.5.0.data/data/docs/savvycan-signal-editor-inverter-temperatures.png
openinverter_can_tool-0.5.0.data/data/docs/shell-completion.md
openinverter_can_tool-0.5.0.data/data/docs/socketcan-config.md
openinverter_can_tool-0.5.0.data/data/docs/upgrader-protocol.md
openinverter_can_tool-0.5.0.dist-info/licenses/LICENSE.txt
openinverter_can_tool-0.5.0.dist-info/METADATA
openinverter_can_tool-0.5.0.dist-info/WHEEL
openinverter_can_tool-0.5.0.dist-info/entry_points.txt
openinverter_can_tool-0.5.0.dist-info/top_level.txt
openinverter_can_tool-0.5.0.dist-info/RECORD
