Metadata-Version: 2.4
Name: openinverter-can-tool
Version: 0.5.0
Summary: Tool to configure and operate OpenInverter systems over CAN
Home-page: https://github.com/davefiddes/openinverter-can-tool
Author: David J. Fiddes
Author-email: D.J@fiddes.net
License: MIT License
Project-URL: Bug Reports, https://github.com/davefiddes/openinverter-can-tool/issues
Project-URL: Source, https://github.com/davefiddes/openinverter-can-tool
Keywords: openinverter,canopen
Classifier: Development Status :: 4 - Beta
Classifier: Environment :: Console
Classifier: Intended Audience :: End Users/Desktop
Classifier: Topic :: Scientific/Engineering
Classifier: Programming Language :: Python :: 3
Classifier: Programming Language :: Python :: 3.9
Classifier: Programming Language :: Python :: 3.10
Classifier: Programming Language :: Python :: 3.11
Classifier: Programming Language :: Python :: 3.12
Classifier: Programming Language :: Python :: 3.13
Classifier: Programming Language :: Python :: 3 :: Only
Requires-Python: >=3.9, <4
License-File: LICENSE.txt
Requires-Dist: click
Requires-Dist: canopen>=2.4.1
Requires-Dist: appdirs
Requires-Dist: python-can[serial]
Requires-Dist: cantools
Provides-Extra: dev
Requires-Dist: check-manifest; extra == "dev"
Requires-Dist: flake8; extra == "dev"
Requires-Dist: pre-commit; extra == "dev"
Provides-Extra: test
Requires-Dist: coverage; extra == "test"
Requires-Dist: pytest; extra == "test"
Requires-Dist: approvaltests; extra == "test"
Requires-Dist: pytest-approvaltests; extra == "test"
Requires-Dist: pytest-cov; extra == "test"
Dynamic: author
Dynamic: author-email
Dynamic: classifier
Dynamic: description
Dynamic: description-content-type
Dynamic: home-page
Dynamic: keywords
Dynamic: license
Dynamic: license-file
Dynamic: project-url
Dynamic: provides-extra
Dynamic: requires-dist
Dynamic: requires-python
Dynamic: summary
